LICENSE.txt
MANIFEST.in
README.md
setup.cfg
setup.py
letsencrypt_s3front/__init__.py
letsencrypt_s3front/authenticator.py
letsencrypt_s3front/installer.py
letsencrypt_s3front.egg-info/PKG-INFO
letsencrypt_s3front.egg-info/SOURCES.txt
letsencrypt_s3front.egg-info/dependency_links.txt
letsencrypt_s3front.egg-info/entry_points.txt
letsencrypt_s3front.egg-info/requires.txt
letsencrypt_s3front.egg-info/top_level.txt
letsencrypt_s3front/tests/__init__.py
letsencrypt_s3front/tests/configurator_test.py
letsencrypt_s3front/tests/nginxparser_test.py
letsencrypt_s3front/tests/obj_test.py
letsencrypt_s3front/tests/parser_test.py
letsencrypt_s3front/tests/tls_sni_01_test.py
letsencrypt_s3front/tests/util.py